{
    "resourceType": "Condition",
    "id": "Condition/1",
    "clinicalStatus": {
        "coding": [
            {
                "system": "http://terminology.hl7.org/CodeSystem/condition-clinical",
                "code": "active",
                "display": "Active"
            }
        ],
        "text": "Active"
    },
    "verificationStatus": {
        "coding": [
            {
                "system": "http://terminology.hl7.org/CodeSystem/condition-ver-status",
                "code": "confirmed",
                "display": "Confirmed"
            }
        ],
        "text": "Confirmed"
    },
    "category": [
        {
            "coding": [
                {
                    "system": "http://terminology.hl7.org/CodeSystem/condition-category",
                    "code": "encounter-diagnosis",
                    "display": "Encounter Diagnosis"
                }
            ],
            "text": "Encounter Diagnosis"
        }
    ],
    "code": {
        "coding": [
            {
                "system": "http://snomed.info/sct",
                "code": "38341003",
                "display": "Hypertension"
            },
            {
                "system": "http://hl7.org/fhir/sid/icd-10-cm",
                "code": "I11.0",
                "display": "Hypertensive heart disease with heart failure"
            }
        ],
        "text": "Hypertension"
    },
    "subject": {
        "reference": "Patient/1",
        "display": "Mr. Shane235 Bartell116"
    },
    "onsetDateTime": "1977-10-17T04:56:37Z",
    "recordedDate": "1977-10-16",
    "recorder": {
        "reference": "Practitioner/1",
        "display": "DR. JANE460 DOE922 MD"
    },
    "asserter": {
        "reference": "Practitioner/1",
        "display": "DR. JANE460 DOE922 MD"
    }
}